physicl/__init__.py
physicl/light.py
physicl/newton.py
physicl-0.0.1.dist-info/LICENSE
physicl-0.0.1.dist-info/METADATA
physicl-0.0.1.dist-info/WHEEL
physicl-0.0.1.dist-info/top_level.txt
physicl-0.0.1.dist-info/RECORD
