Metadata-Version: 2.1
Name: physicl
Version: 0.0.1
Summary: OpenCL-based physics simulation package
Home-page: https://github.com/bcwarner/physics-sim
Author: Ben Warner
Author-email: warnerbc@plu.edu
License: UNKNOWN
Platform: UNKNOWN
Classifier: Programming Language :: Python :: 3
Classifier: License :: OSI Approved :: MIT License
Classifier: Operating System :: OS Independent
Classifier: Framework :: Pytest
Classifier: Intended Audience :: Education
Classifier: Intended Audience :: Science/Research
Classifier: Development Status :: 3 - Alpha
Requires-Python: >=3.6
Requires-Dist: numpy
Requires-Dist: pyopencl
Requires-Dist: pytest
Requires-Dist: scipy
